tfc/__init__.py
tfc/__main__.py
tfc/cli.py
tfc/client.py
tfc/message_variables.py
terraform_cloud_client-0.0.3.dist-info/LICENSE
terraform_cloud_client-0.0.3.dist-info/METADATA
terraform_cloud_client-0.0.3.dist-info/WHEEL
terraform_cloud_client-0.0.3.dist-info/entry_points.txt
terraform_cloud_client-0.0.3.dist-info/top_level.txt
terraform_cloud_client-0.0.3.dist-info/RECORD
