Metadata-Version: 2.1
Name: terraform-cloud-client
Version: 0.0.3
Summary: A client for HashiCorp Terraform Cloud
Home-page: https://github.com/octoenergy/terraform-cloud-client
Author: Kraken Technologies Limited
Author-email: talent@octopus.energy
License: UNKNOWN
Platform: UNKNOWN
Classifier: Programming Language :: Python :: 3
Classifier: License :: OSI Approved :: MIT License
Classifier: Operating System :: OS Independent
